{"name":"代码优化","slug":"代码优化","count":2,"postlist":[{"title":"11 个 JavaScript 单行代码技巧","uid":"d6d6a7d81f75ad96a8fb728f1eea1f5d","slug":"11个JavaScript单行代码技巧","date":"2021-09-21T09:51:00.000Z","updated":"2021-12-17T09:54:03.000Z","comments":true,"path":"api/articles/11个JavaScript单行代码技巧.json","keywords":null,"cover":"https://s4.ax1x.com/2022/01/18/70HjaV.png","text":"前言美总是简单和谐的，代码也是一样 用简单的逻辑和尽可能少的代码来解决一个复杂的问题。随着 ES6 箭头函数的引入，可以创建看起来优雅和简单的单行代码。 给大家分享 11 个 JavaScript 单行代码技巧 1、获取字符串中的字符数 获取字符数是一个有用的实用程序，在许多情况...","link":"","photos":[],"count_time":{"symbolsCount":"2.9k","symbolsTime":"3 mins."},"categories":[{"name":"学习笔记","slug":"学习笔记","count":2,"path":"api/categories/学习笔记.json"}],"tags":[{"name":"JavaScript","slug":"JavaScript","count":2,"path":"api/tags/JavaScript.json"},{"name":"代码优化","slug":"代码优化","count":2,"path":"api/tags/代码优化.json"}],"author":{"name":"XSTAR","slug":"blog-author","avatar":"https://s4.ax1x.com/2022/01/15/7JGwhF.jpg","link":"/","description":"正在创作一切未来","socials":{"github":"https://github.com/oygs","twitter":"","stackoverflow":"","wechat":"","qq":"","weibo":"","zhihu":"","csdn":"","juejin":"","customs":{}}}},{"title":"VUE3 UI框架推荐","uid":"10d16c76e89712ec4917e342502d52cc","slug":"2021-11-08-VUE3_UI框架推荐","date":"2021-11-08T10:39:00.000Z","updated":"2021-12-17T10:42:28.000Z","comments":true,"path":"api/articles/2021-11-08-VUE3_UI框架推荐.json","keywords":null,"cover":"https://s4.ax1x.com/2022/01/18/7B99DU.png","text":"本文推荐几个比较流行的VUE3 UI框架 同时提供出色的开发人员体验，合理利用，又或者学习借鉴都是不错的选择，排名不分先后。 Ant Design Vue官方网站：https://2x.antdv.com/components/overview/ Ant Design Vue 是...","link":"","photos":[],"count_time":{"symbolsCount":828,"symbolsTime":"1 mins."},"categories":[{"name":"随笔记录","slug":"随笔记录","count":7,"path":"api/categories/随笔记录.json"}],"tags":[{"name":"代码优化","slug":"代码优化","count":2,"path":"api/tags/代码优化.json"},{"name":"框架推荐","slug":"框架推荐","count":1,"path":"api/tags/框架推荐.json"}],"author":{"name":"XSTAR","slug":"blog-author","avatar":"https://s4.ax1x.com/2022/01/15/7JGwhF.jpg","link":"/","description":"正在创作一切未来","socials":{"github":"https://github.com/oygs","twitter":"","stackoverflow":"","wechat":"","qq":"","weibo":"","zhihu":"","csdn":"","juejin":"","customs":{}}}}]}